{
  "Drivers" : {
    "alonso" : {
      "cost": 11.9,
      "points_history" : [28, 24, 24, 24, 16]
    },
    "bottas" : {
      "cost": 25,
      "points_history" : [19, 37, 37, 7, 31]
    },
    "ericsson" : {
      "cost": 5.9,
      "points_history" : [-12, 19, 13, 12, 10]
    },
    "gasly" : {
      "cost": 6.5,
      "points_history" : [-14, 28, 4, 14, -11]
    },
    "grosjean" : {
      "cost": 5.6,
      "points_history" :  [-8, 8, -3, -20, -11]
    },
    "hamilton" : {
      "cost": 31.1,
      "points_history" : [35, 36, 23, 45, 44]
    },
    "hartley" : {
      "cost": 7.3,
      "points_history" : [9, -2, -11, 10, 9]
    },
    "hulkenberg" : {
      "cost": 10.5,
      "points_history" : [18, 22, 23, -8, -14]
    },
    "leclerc" : {
      "cost": 6.1,
      "points_history" : [15, 12, 4, 26, 17]
    },
    "magnussen" : {
      "cost": 8,
      "points_history" : [-5, 25, 9, 12, 23]
    },
    "ocon" : {
      "cost": 9.6,
      "points_history" : [7, 8, 8, -6, -11]
    },
    "perez" : {
      "cost": 13.2,
      "points_history" : [10, -1, 1, 35, 18]
    },
    "raikonnen" : {
      "cost": 18.9,
      "points_history" : [28, -3, 29, 38, -5]
    },
    "ricciardo" : {
      "cost": 20.2,
      "points_history" : [33, -4, 47, -3, 26]
    },
    "sainz" : {
      "cost": 10.8,
      "points_history" : [9, 3, 8, 26, 21]
    },
    "sirotkin" : {
      "cost": 7.4,
      "points_history" : [-14, 10, 6, -13, 14]
    },
    "stroll" : {
      "cost": 9.3,
      "points_history" : [7, 15, 13, 16, 15]
    },
    "vandoorne" : {
      "cost": 7,
      "points_history" : [9, 17, 5, 14, -13]
    },
    "verstappen" : {
      "cost": 19.7,
      "points_history" : [17, -13, 22, -6, 34]
    },
    "vettel" : {
      "cost": 27.6,
      "points_history" : [44, 44, 10, 22, 27]
    }
  },
  "Constructors" : {
    "mercedes": {
      "cost" : 31.3,
      "points_history": [49, 69, 55, 42, 70]
    },
    "ferrari": {
      "cost" : 27.6,
      "points_history": [67, 51, 34, 55, 32]
    },
    "red bull": {
      "cost" : 20,
      "points_history": [45, 11, 64, 19, 50]
    },
    "force india": {
      "cost" : 11.4,
      "points_history": [12, 2, 4, 39, 17]
    },
    "williams": {
      "cost" : 9.8,
      "points_history": [-12, 20, 19, 13, 24]
    },
    "renault": {
      "cost" : 10.2,
      "points_history": [22, 20, 26, 28, 17]
    },
    "toro rosso": {
      "cost" : 8.2,
      "points_history": [-10, 21, 3, 24, 13]
    },
    "haas": {
      "cost" : 6,
      "points_history": [15, 28, 1, 7, 22]
    },
    "mclaren": {
      "cost" : 9.6,
      "points_history": [31, 36, 26, 33, 13]
    },
    "sauber": {
      "cost" : 6.7,
      "points_history": [-2, 28, 12, 33, 22]
    }
  }
}